injected/__init__.py
injected/_base.py
injected/_version.py
injected/py.typed
injected-0.2.2.dist-info/licenses/LICENSE
injected-0.2.2.dist-info/METADATA
injected-0.2.2.dist-info/WHEEL
injected-0.2.2.dist-info/top_level.txt
injected-0.2.2.dist-info/RECORD
