Metadata-Version: 2.4
Name: injected
Version: 0.2.2
Summary: Simple, type-safe dependency injection
Author-email: Anton Agestam <git@antonagestam.se>
License-Expression: BSD-3-Clause
Project-URL: Source Repository, https://github.com/antonagestam/injected/
Project-URL: Bug Tracker, https://github.com/antonagestam/injected/issues
Classifier: Intended Audience :: Developers
Classifier: Operating System :: OS Independent
Classifier: Programming Language :: Python
Classifier: Programming Language :: Python :: 3
Classifier: Programming Language :: Python :: 3 :: Only
Classifier: Programming Language :: Python :: 3.13
Classifier: Programming Language :: Python :: 3.14
Classifier: Development Status :: 4 - Beta
Classifier: Typing :: Typed
Requires-Python: >=3.13
License-File: LICENSE
Requires-Dist: immutables>=0.21
Provides-Extra: test
Requires-Dist: mypy; extra == "test"
Requires-Dist: pytest; extra == "test"
Requires-Dist: pytest-asyncio; extra == "test"
Requires-Dist: pytest-markdown-docs; extra == "test"
Requires-Dist: pytest-mypy-plugins; extra == "test"
Requires-Dist: pytest-random-order; extra == "test"
Requires-Dist: coverage; extra == "test"
Dynamic: license-file
